libcalab/FreeImage.dll
libcalab/MotionGraph.py
libcalab/__init__.py
libcalab/config.py
libcalab/controlmodule.py
libcalab/default_settings.py
libcalab/filechooser.py
libcalab/filechooser_mac.py
libcalab/filechooser_wx.py
libcalab/libmainlib.cp312-win_arm64.pyd
libcalab/luamodule.py
libcalab/rendermodule.py
libcalab/test_sample_python.py
libcalab/Resource/default/colormap.bmp
libcalab/Resource/motion/MOB1/hanyang_lowdof_T.con_config.lua
libcalab/Resource/motion/humanHanyang/hanyang_lowdof_M.con_config.lua
libcalab/Resource/motion/humanHanyang/hanyang_lowdof_M.retargetConfig.lua
libcalab/Resource/motion/humanHanyang/hanyang_lowdof_M.wrl
libcalab/Resource/scripts/DAEloader.lua
libcalab/Resource/scripts/FBXloader.lua
libcalab/Resource/scripts/FBXloader_lua.lua
libcalab/Resource/scripts/FBXloader_tools.lua
libcalab/Resource/scripts/Mixamo.lua
libcalab/Resource/scripts/README_LUA
libcalab/Resource/scripts/_ogre_module.lua
libcalab/Resource/scripts/common.lua
libcalab/Resource/scripts/debugger.lua
libcalab/Resource/scripts/dummyGUI.lua
libcalab/Resource/scripts/evaluations.lua
libcalab/Resource/scripts/json.lua
libcalab/Resource/scripts/module.lua
libcalab/Resource/scripts/moduleGraph.lua
libcalab/Resource/scripts/moduleIK.lua
libcalab/Resource/scripts/module_nativeLua.lua
libcalab/Resource/scripts/module_onlineMotionEdit.lua
libcalab/Resource/scripts/mylib.lua
libcalab/Resource/scripts/mylib_debugger.lua
libcalab/Resource/scripts/mylib_filesystem.lua
libcalab/Resource/scripts/pyMrdplot.lua
libcalab/Resource/scripts/tl.lua
libcalab/Resource/scripts/Kinematics/arc.lua
libcalab/Resource/scripts/Kinematics/meshTools.lua
libcalab/Resource/scripts/Kinematics/unityHelper.lua
libcalab/Resource/scripts/RigidBodyWin/RagdollFall.lua
libcalab/Resource/scripts/RigidBodyWin/Segmentation.lua
libcalab/Resource/scripts/RigidBodyWin/_doesNothing.lua
libcalab/Resource/scripts/RigidBodyWin/cameraTracker.lua
libcalab/Resource/scripts/RigidBodyWin/console.lua
libcalab-0.2.4.dist-info/METADATA
libcalab-0.2.4.dist-info/WHEEL
libcalab-0.2.4.dist-info/top_level.txt
libcalab-0.2.4.dist-info/RECORD
