Metadata-Version: 2.4
Name: libcalab
Version: 0.2.4
Summary: This is a library for character animation with no GUI (console-mode). For rendering, please use libcalab_ogre3d (ogre-next) or GitHub:taesoobear/libcalab_examples (ogre-python) instead.
Author-email: Taesoo <taesoobear@gmail.com>
License: MIT
Requires-Python: ==3.12.*
Dynamic: requires-python
